{
  "minecraft:recipes/redstone/dispenser": {
    "criteria": {
      "has_bow": "2022-06-22 13:09:24 +0000"
    },
    "done": true
  },
  "minecraft:recipes/building_blocks/emerald_block": {
    "criteria": {
      "has_emerald": "2022-06-22 13:08:46 +0000"
    },
    "done": true
  },
  "minecraft:recipes/misc/beacon": {
    "criteria": {
      "has_nether_star": "2022-06-22 13:07:45 +0000"
    },
    "done": true
  },
  "minecraft:adventure/adventuring_time": {
    "criteria": {
      "minecraft:forest": "2022-06-22 13:07:44 +0000",
      "minecraft:plains": "2022-06-22 13:08:46 +0000"
    },
    "done": false
  },
  "DataVersion": 2730
}